mt/iio/__init__.py
mt/imageio/__init__.py
mt/imageio/immview.py
mt/imageio/imread.py
mt/imageio/imwrite.py
mt/imageio/version.py
mtimageio-0.5.14.data/scripts/immview
mtimageio-0.5.14.dist-info/licenses/LICENSE
mtimageio-0.5.14.dist-info/METADATA
mtimageio-0.5.14.dist-info/WHEEL
mtimageio-0.5.14.dist-info/top_level.txt
mtimageio-0.5.14.dist-info/RECORD
