Metadata-Version: 2.4
Name: mtimageio
Version: 0.5.14
Summary: Minh-Tri Pham's extra modules using imageio
Author: ['Minh-Tri Pham']
License-File: LICENSE
Requires-Dist: Pillow>=9.0
Requires-Dist: imageio>=2.15
Requires-Dist: mtbase>=4.33.2
Requires-Dist: mtopencv>=1.11.2
Dynamic: author
Dynamic: license-file
Dynamic: requires-dist
Dynamic: summary
